LICENSE
cloudcheck/__init__.py
cloudcheck/__main__.py
cloudcheck/lib/akamai.py
cloudcheck/lib/aws.py
cloudcheck/lib/azure.py
cloudcheck/lib/cache/cache.json
cloudcheck/lib/cloudflare.py
cloudcheck/lib/fastly.py
cloudcheck/lib/google.py
cloudcheck/lib/incapsula.py
cloudcheck/lib/sucuri.py
cloudcheckr-0.1.0.dist-info/entry_points.txt
cloudcheckr-0.1.0.dist-info/LICENSE
cloudcheckr-0.1.0.dist-info/WHEEL
cloudcheckr-0.1.0.dist-info/METADATA
cloudcheckr-0.1.0.dist-info/RECORD
