Metadata-Version: 2.1
Name: cloudcheckr
Version: 0.1.0
Summary: 
Home-page: https://github.com/puzzlepeaches/cloudcheck
License: BSD 3-Clause License
Author: Nicholas
Author-email: nanastasi@sprocketsecurity.com
Requires-Python: >=3.8,<4.0
Classifier: Environment :: Console
Classifier: License :: Other/Proprietary License
Classifier: Programming Language :: Python :: 3
Classifier: Programming Language :: Python :: 3.8
Classifier: Programming Language :: Python :: 3.9
Classifier: Programming Language :: Python :: 3.10
Classifier: Programming Language :: Python :: 3.11
Classifier: Programming Language :: Python :: 3
Classifier: Topic :: Security
Requires-Dist: bs4 (>=0.0.1,<0.0.2)
Requires-Dist: click
Requires-Dist: click-config-file
Requires-Dist: requests (>=2.27.1,<3.0.0)
Requires-Dist: rich
Project-URL: Repository, https://github.com/puzzlepeaches/cloudcheck
